appchance_cli/__init__.py
appchance_cli/ace/__init__.py
appchance_cli/ace/ace.py
appchance_cli-0.1.3.2.data/scripts/ace
appchance_cli-0.1.3.2.dist-info/METADATA
appchance_cli-0.1.3.2.dist-info/WHEEL
appchance_cli-0.1.3.2.dist-info/top_level.txt
appchance_cli-0.1.3.2.dist-info/RECORD
