Metadata-Version: 2.1
Name: appchance-cli
Version: 0.1.3.2
Summary: Developers toolkit for Appchance Python backend team.Also spell book for wizards and ninjas - useful in dungeons.
Home-page: https://bitbucket.org/appchance/appchance-tools/
Author: Appchance Python Team
Author-email: backend@appchance.com
License: UNKNOWN
Platform: UNKNOWN
Classifier: Programming Language :: Python :: 3.8
Classifier: Operating System :: POSIX :: Linux
Requires-Python: >=3.8
Requires-Dist: fire (==0.3.1)
Requires-Dist: wheel
Requires-Dist: twine
